os_lib/__init__.py
os_lib/os_lib.py
os_lib-1.0.0.dist-info/METADATA
os_lib-1.0.0.dist-info/WHEEL
os_lib-1.0.0.dist-info/top_level.txt
os_lib-1.0.0.dist-info/RECORD
