Metadata-Version: 2.1
Name: os-lib
Version: 1.0.0
Summary: A simple library to get numbers from 1 to 6
Author: Nilesh Patil
Author-email: patil53nilesh@gmail.com
